Metadata-Version: 2.1
Name: odoo-addon-payment_redsys
Version: 18.0.1.0.1.1
Requires-Python: >=3.10
Requires-Dist: odoo==18.0.*
Requires-Dist: pycryptodome
Summary: Payment Acquirer: Redsys Implementation
Home-page: https://github.com/OCA/l10n-spain
License: AGPL-3
Author: Tecnativa, Odoo Community Association (OCA)
Author-email: support@odoo-community.org
Classifier: Programming Language :: Python
Classifier: Framework :: Odoo
Classifier: Framework :: Odoo :: 18.0
Classifier: License :: OSI Approved :: GNU Affero General Public License v3
